odeta/__init__.py
odeta/cloudbase.py
odeta/localbase.py
odeta/test.py
odeta/utils.py
odeta-0.3.1.dist-info/licenses/LICENSE
odeta-old/__init__.py
odeta-old/a.py
odeta-old/cloudbase.py
odeta-old/localbase.py
odeta-old/utils.py
odeta-0.3.1.dist-info/METADATA
odeta-0.3.1.dist-info/WHEEL
odeta-0.3.1.dist-info/top_level.txt
odeta-0.3.1.dist-info/RECORD
