Metadata-Version: 2.4
Name: odeta
Version: 0.3.1
Summary: A simple NoSQL-like interface for SQLite
Home-page: https://github.com/malwaremanu/odeta
Author: Manupal Choudhary
Author-email: tech.manujpr@gmail.com
Classifier: Programming Language :: Python :: 3
Classifier: License :: OSI Approved :: MIT License
Classifier: Operating System :: OS Independent
Requires-Python: >=3.6
License-File: LICENSE
Requires-Dist: pymongo
Dynamic: author
Dynamic: author-email
Dynamic: classifier
Dynamic: description
Dynamic: description-content-type
Dynamic: home-page
Dynamic: license-file
Dynamic: requires-dist
Dynamic: requires-python
Dynamic: summary
